stactools/corine/__init__.py
stactools/corine/cog.py
stactools/corine/commands.py
stactools/corine/constants.py
stactools/corine/stac.py
stactools/corine/version.py
stactools_corine-0.1.6.dist-info/METADATA
stactools_corine-0.1.6.dist-info/WHEEL
stactools_corine-0.1.6.dist-info/top_level.txt
stactools_corine-0.1.6.dist-info/RECORD
